AutogitPy/__init__.py
AutogitPy-0.0.3.dist-info/LICENSE.txt
AutogitPy-0.0.3.dist-info/METADATA
AutogitPy-0.0.3.dist-info/WHEEL
AutogitPy-0.0.3.dist-info/top_level.txt
AutogitPy-0.0.3.dist-info/RECORD
