Metadata-Version: 2.1
Name: AutogitPy
Version: 0.0.3
Summary: A package which automates the process of git
Home-page: https://github.com/BloreDataPlayers/AutogitPy
Author: Saran,Abhilash,Abhiraman,Tarun
Author-email: unofficialcredentials@gmail.com
License: MIT
Keywords: configuration core yaml ini json environment
Platform: UNKNOWN
Classifier: Programming Language :: Python :: 3
Classifier: License :: OSI Approved :: MIT License
Classifier: Operating System :: OS Independent
Requires-Python: >=3.6
